setup.py
swing/__init__.py
swing/basic.py
swing.egg-info/PKG-INFO
swing.egg-info/SOURCES.txt
swing.egg-info/dependency_links.txt
swing.egg-info/top_level.txt
tests/__init__.py