Metadata-Version: 1.1
Name: swing
Version: 0.0.3
Summary: Configuration switcher by an environment variable inspired by Common Lisp's envy
Home-page: https://github.com/monklof/swing
Author: monklof
Author-email: monklof@gmail.com
License: MIT
Keywords: configuration switcher,configuration management
Platform: UNKNOWN
Classifier: Development Status :: 2 - Pre-Alpha
Classifier: Topic :: Utilities
Classifier: License :: OSI Approved :: MIT License
